setup.py
ized/__init__.py
ized/expand.py
ized/gcv.py
ized/glm.py
ized/qr.py
ized/utils.py
ized.egg-info/PKG-INFO
ized.egg-info/SOURCES.txt
ized.egg-info/dependency_links.txt
ized.egg-info/top_level.txt