Metadata-Version: 1.1
Name: ized
Version: 0.0.2
Summary: Spline expansions, multiple regularizers, and generalized linear models
Home-page: UNKNOWN
Author: Ingo Fruend
Author-email: ized@ingofruend.net
License: MIT
Platform: UNKNOWN
Classifier: Development Status :: 3 - Alpha
Classifier: Intended Audience :: Science/Research
Classifier: License :: OSI Approved :: MIT License
Classifier: Programming Language :: Python
Classifier: Topic :: Scientific/Engineering :: Mathematics
